ragtime/__init__.py
ragtime/base.py
ragtime/config.py
ragtime/expe.py
ragtime/pipeline.py
ragtime/base_folder/.gitignore
ragtime/base_folder/LICENSE
ragtime/base_folder/README.md
ragtime/base_folder/classes.py
ragtime/base_folder/main.py
ragtime/base_folder/expe/01. Questions/json_helper.xlsx
ragtime/base_folder/res/html_templates/basic_template.jinja
ragtime/base_folder/res/spreadsheet_templates/MCQ.xlsx
ragtime/base_folder/res/spreadsheet_templates/first_questions.xlsx
ragtime/base_folder/res/spreadsheet_templates/test_facts.xlsx
ragtime/base_folder/res/spreadsheet_templates/with_chunks.xlsx
ragtime/base_folder/res/spreadsheet_templates/without_chunks.xlsx
ragtime/base_folder/res/spreadsheet_templates/old/basic_template_old.xlsx
ragtime/base_folder/res/spreadsheet_templates/old/spreadsheet_rich_template.xlsx
ragtime/generators/__init__.py
ragtime/generators/answer_generator.py
ragtime/generators/eval_generator.py
ragtime/generators/fact_generator.py
ragtime/generators/question_generator.py
ragtime/generators/text_generator.py
ragtime/llms/__init__.py
ragtime/llms/lite_llm.py
ragtime/llms/llm.py
ragtime/prompters/__init__.py
ragtime/prompters/answer_prompters.py
ragtime/prompters/eval_prompters.py
ragtime/prompters/fact_prompters.py
ragtime/prompters/prompter.py
ragtime/prompters/question_prompters.py
ragtime/retrievers/__init__.py
ragtime/retrievers/indexer.py
ragtime/retrievers/retriever.py
ragtime-0.0.43.dist-info/METADATA
ragtime-0.0.43.dist-info/WHEEL
ragtime-0.0.43.dist-info/licenses/LICENSE
ragtime-0.0.43.dist-info/RECORD
