Metadata-Version: 2.3
Name: ragtime
Version: 0.0.43
Summary: Ragtime 🎹 is an LLMOps framework to automatically evaluate Retrieval Augmented Generation (RAG) systems and compare different RAGs / LLMs
Project-URL: Homepage, https://github.com/recitalAI/ragtime-package
Project-URL: Issues, https://github.com/recitalAI/ragtime-package/issues
Author-email: Gilles Moyse <gilles@recital.ai>
Maintainer-email: reciTAL <ragtime@recital.ai>
License: MIT License
License-File: LICENSE
Keywords: Evaluation,LLM,RAG
Classifier: Development Status :: 3 - Alpha
Classifier: License :: OSI Approved :: MIT License
Classifier: Operating System :: OS Independent
Classifier: Programming Language :: Python :: 3
Requires-Python: >=3.9
Requires-Dist: asyncio
Requires-Dist: jinja2
Requires-Dist: langdetect
Requires-Dist: lazy-import
Requires-Dist: litellm
Requires-Dist: llama-index
Requires-Dist: openpyxl
Requires-Dist: pathlib
Requires-Dist: py-setenv
Requires-Dist: pydantic
Requires-Dist: requests
Requires-Dist: retry
Requires-Dist: setenv
Requires-Dist: tabulate
Requires-Dist: unidecode
